README.md
pyproject.toml
setup.cfg
setup.py
./CMakeLists.txt
./patches/shared_lib.patch
lyncs_clime/__init__.py
lyncs_clime/lib.py
lyncs_clime/reader.py
lyncs_clime/status.py
lyncs_clime.egg-info/PKG-INFO
lyncs_clime.egg-info/SOURCES.txt
lyncs_clime.egg-info/dependency_links.txt
lyncs_clime.egg-info/entry_points.txt
lyncs_clime.egg-info/requires.txt
lyncs_clime.egg-info/top_level.txt
test/__init__.py
test/conf.unity
test/test_reader.py