Metadata-Version: 2.1
Name: lyncs-clime
Version: 0.1.0
Summary: A Python interface to c-lime for Lyncs
Home-page: https://lyncs-api.github.io
Author: Simone Bacchio
Author-email: s.bacchio@gmail.com
License: UNKNOWN
Download-URL: https://github.com/Lyncs-API/lyncs.clime
Keywords: Lyncs,c-lime,Lattice QCD
Platform: UNKNOWN
Classifier: Development Status :: 2 - Pre-Alpha
Classifier: Intended Audience :: Developers
Classifier: Intended Audience :: Education
Classifier: Intended Audience :: Science/Research
Classifier: License :: OSI Approved :: BSD License
Classifier: Natural Language :: English
Classifier: Operating System :: Unix
Classifier: Programming Language :: C
Classifier: Programming Language :: C++
Classifier: Programming Language :: Python :: 3 :: Only
Classifier: Topic :: Scientific/Engineering :: Physics
Provides-Extra: test
Provides-Extra: all
